pgheader.py
setup.cfg
setup.py
pgheader.egg-info/PKG-INFO
pgheader.egg-info/SOURCES.txt
pgheader.egg-info/dependency_links.txt
pgheader.egg-info/top_level.txt