Metadata-Version: 1.1
Name: pgheader
Version: 1.0
Summary: Retrieve information in the Postgres custom dump header using Python
Home-page: https://github.com/cecton/pg_header.py
Author: Cecile Tonglet
Author-email: cecile.tonglet@gmail.com
License: MIT
Keywords: postgres database dump header
Platform: UNKNOWN
Classifier: Development Status :: 5 - Production/Stable
Classifier: Topic :: Database
Classifier: License :: OSI Approved :: MIT License
